ocp_mcp_server/__init__.py
ocp_mcp_server/server.py
okctl_mcp_server/__init__.py
okctl_mcp_server/server.py
okctl_mcp_server/tools/__init__.py
okctl_mcp_server/tools/backup_policy.py
okctl_mcp_server/tools/clusters.py
okctl_mcp_server/tools/components.py
okctl_mcp_server/tools/install.py
okctl_mcp_server/tools/sql.py
okctl_mcp_server/tools/tenants.py
okctl_mcp_server/utils/errors.py
mseep_mcp_oceanbase-0.1.4.dist-info/METADATA
mseep_mcp_oceanbase-0.1.4.dist-info/WHEEL
mseep_mcp_oceanbase-0.1.4.dist-info/entry_points.txt
mseep_mcp_oceanbase-0.1.4.dist-info/licenses/LICENSE
mseep_mcp_oceanbase-0.1.4.dist-info/RECORD
